imagelab/__init__.py
imagelab/camera.py
imagelab/construct.py
imagelab/io.py
imagelab/phaseshift.py
imagelab/pointcloud.py
imagelab/utilities.py
imagelab-0.1.0.dist-info/WHEEL
imagelab-0.1.0.dist-info/METADATA
imagelab-0.1.0.dist-info/RECORD
