Metadata-Version: 2.1
Name: imagelab
Version: 0.1.0
Summary: This package is DTU Compute imagelab SDK for research in image analysis, computer vision, and computational imaging.
License: MIT
Author: Søren K. S. Gregersen
Author-email: sorgre@dtu.dk
Requires-Python: >=3.7,<4.0
Classifier: License :: OSI Approved :: MIT License
Classifier: Programming Language :: Python :: 3
Classifier: Programming Language :: Python :: 3.7
Classifier: Programming Language :: Python :: 3.8
Requires-Dist: numpy (>=1.17.2,<2.0.0)
Requires-Dist: opencv-contrib-python (>=4.4.0,<5.0.0)
Requires-Dist: scipy (>=1.5.2,<2.0.0)
